[{"courier_id": 101, "action": "pickup", "order_id": 17209, "point_id": 47209}, {"courier_id": 101, "action": "dropoff", "order_id": 17209, "point_id": 67209}, {"courier_id": 233, "action": "pickup", "order_id": 17176, "point_id": 47176}, {"courier_id": 233, "action": "dropoff", "order_id": 17176, "point_id": 67176}, {"courier_id": 1, "action": "pickup", "order_id": 10772, "point_id": 40772}, {"courier_id": 1, "action": "dropoff", "order_id": 10772, "point_id": 60772}, {"courier_id": 2, "action": "pickup", "order_id": 12910, "point_id": 42910}, {"courier_id": 2, "action": "dropoff", "order_id": 12910, "point_id": 62910}, {"courier_id": 3, "action": "pickup", "order_id": 16817, "point_id": 46817}, {"courier_id": 3, "action": "dropoff", "order_id": 16817, "point_id": 66817}, {"courier_id": 4, "action": "pickup", "order_id": 17230, "point_id": 47230}, {"courier_id": 4, "action": "dropoff", "order_id": 17230, "point_id": 67230}, {"courier_id": 5, "action": "pickup", "order_id": 17273, "point_id": 47273}, {"courier_id": 5, "action": "dropoff", "order_id": 17273, "point_id": 67273}, {"courier_id": 6, "action": "pickup", "order_id": 17303, "point_id": 47303}, {"courier_id": 6, "action": "dropoff", "order_id": 17303, "point_id": 67303}, {"courier_id": 143, "action": "pickup", "order_id": 17212, "point_id": 47212}, {"courier_id": 143, "action": "dropoff", "order_id": 17212, "point_id": 67212}, {"courier_id": 15, "action": "pickup", "order_id": 17280, "point_id": 47280}, {"courier_id": 15, "action": "dropoff", "order_id": 17280, "point_id": 67280}, {"courier_id": 7, "action": "pickup", "order_id": 10657, "point_id": 40657}, {"courier_id": 7, "action": "dropoff", "order_id": 10657, "point_id": 60657}, {"courier_id": 8, "action": "pickup", "order_id": 10937, "point_id": 40937}, {"courier_id": 8, "action": "dropoff", "order_id": 10937, "point_id": 60937}, {"courier_id": 9, "action": "pickup", "order_id": 14775, "point_id": 44775}, {"courier_id": 9, "action": "dropoff", "order_id": 14775, "point_id": 64775}, {"courier_id": 10, "action": "pickup", "order_id": 16070, "point_id": 46070}, {"courier_id": 10, "action": "dropoff", "order_id": 16070, "point_id": 66070}, {"courier_id": 11, "action": "pickup", "order_id": 17099, "point_id": 47099}, {"courier_id": 11, "action": "dropoff", "order_id": 17099, "point_id": 67099}, {"courier_id": 12, "action": "pickup", "order_id": 17168, "point_id": 47168}, {"courier_id": 12, "action": "dropoff", "order_id": 17168, "point_id": 67168}, {"courier_id": 13, "action": "pickup", "order_id": 17234, "point_id": 47234}, {"courier_id": 13, "action": "dropoff", "order_id": 17234, "point_id": 67234}, {"courier_id": 14, "action": "pickup", "order_id": 17248, "point_id": 47248}, {"courier_id": 14, "action": "dropoff", "order_id": 17248, "point_id": 67248}, {"courier_id": 16, "action": "pickup", "order_id": 17258, "point_id": 47258}, {"courier_id": 16, "action": "dropoff", "order_id": 17258, "point_id": 67258}, {"courier_id": 17, "action": "pickup", "order_id": 17302, "point_id": 47302}, {"courier_id": 17, "action": "dropoff", "order_id": 17302, "point_id": 67302}, {"courier_id": 185, "action": "pickup", "order_id": 17146, "point_id": 47146}, {"courier_id": 185, "action": "dropoff", "order_id": 17146, "point_id": 67146}, {"courier_id": 256, "action": "pickup", "order_id": 17269, "point_id": 47269}, {"courier_id": 256, "action": "dropoff", "order_id": 17269, "point_id": 67269}, {"courier_id": 116, "action": "pickup", "order_id": 16480, "point_id": 46480}, {"courier_id": 116, "action": "dropoff", "order_id": 16480, "point_id": 66480}, {"courier_id": 134, "action": "pickup", "order_id": 16840, "point_id": 46840}, {"courier_id": 134, "action": "dropoff", "order_id": 16840, "point_id": 66840}, {"courier_id": 172, "action": "pickup", "order_id": 17277, "point_id": 47277}, {"courier_id": 172, "action": "dropoff", "order_id": 17277, "point_id": 67277}, {"courier_id": 57, "action": "pickup", "order_id": 10217, "point_id": 40217}, {"courier_id": 57, "action": "dropoff", "order_id": 10217, "point_id": 60217}, {"courier_id": 18, "action": "pickup", "order_id": 10591, "point_id": 40591}, {"courier_id": 18, "action": "dropoff", "order_id": 10591, "point_id": 60591}, {"courier_id": 19, "action": "pickup", "order_id": 12812, "point_id": 42812}, {"courier_id": 19, "action": "dropoff", "order_id": 12812, "point_id": 62812}, {"courier_id": 20, "action": "pickup", "order_id": 15675, "point_id": 45675}, {"courier_id": 20, "action": "dropoff", "order_id": 15675, "point_id": 65675}, {"courier_id": 21, "action": "pickup", "order_id": 16035, "point_id": 46035}, {"courier_id": 21, "action": "dropoff", "order_id": 16035, "point_id": 66035}, {"courier_id": 22, "action": "pickup", "order_id": 16641, "point_id": 46641}, {"courier_id": 22, "action": "dropoff", "order_id": 16641, "point_id": 66641}, {"courier_id": 23, "action": "pickup", "order_id": 16702, "point_id": 46702}, {"courier_id": 23, "action": "dropoff", "order_id": 16702, "point_id": 66702}, {"courier_id": 24, "action": "pickup", "order_id": 16741, "point_id": 46741}, {"courier_id": 24, "action": "dropoff", "order_id": 16741, "point_id": 66741}, {"courier_id": 25, "action": "pickup", "order_id": 16855, "point_id": 46855}, {"courier_id": 25, "action": "dropoff", "order_id": 16855, "point_id": 66855}, {"courier_id": 26, "action": "pickup", "order_id": 17066, "point_id": 47066}, {"courier_id": 26, "action": "dropoff", "order_id": 17066, "point_id": 67066}, {"courier_id": 27, "action": "pickup", "order_id": 17084, "point_id": 47084}, {"courier_id": 27, "action": "dropoff", "order_id": 17084, "point_id": 67084}, {"courier_id": 28, "action": "pickup", "order_id": 17135, "point_id": 47135}, {"courier_id": 28, "action": "dropoff", "order_id": 17135, "point_id": 67135}, {"courier_id": 29, "action": "pickup", "order_id": 17171, "point_id": 47171}, {"courier_id": 29, "action": "dropoff", "order_id": 17171, "point_id": 67171}, {"courier_id": 30, "action": "pickup", "order_id": 17214, "point_id": 47214}, {"courier_id": 30, "action": "dropoff", "order_id": 17214, "point_id": 67214}, {"courier_id": 31, "action": "pickup", "order_id": 17217, "point_id": 47217}, {"courier_id": 31, "action": "dropoff", "order_id": 17217, "point_id": 67217}, {"courier_id": 32, "action": "pickup", "order_id": 17226, "point_id": 47226}, {"courier_id": 32, "action": "dropoff", "order_id": 17226, "point_id": 67226}, {"courier_id": 33, "action": "pickup", "order_id": 17239, "point_id": 47239}, {"courier_id": 33, "action": "dropoff", "order_id": 17239, "point_id": 67239}, {"courier_id": 34, "action": "pickup", "order_id": 17244, "point_id": 47244}, {"courier_id": 34, "action": "dropoff", "order_id": 17244, "point_id": 67244}, {"courier_id": 35, "action": "pickup", "order_id": 17249, "point_id": 47249}, {"courier_id": 35, "action": "dropoff", "order_id": 17249, "point_id": 67249}, {"courier_id": 36, "action": "pickup", "order_id": 17254, "point_id": 47254}, {"courier_id": 36, "action": "dropoff", "order_id": 17254, "point_id": 67254}, {"courier_id": 37, "action": "pickup", "order_id": 17275, "point_id": 47275}, {"courier_id": 37, "action": "dropoff", "order_id": 17275, "point_id": 67275}, {"courier_id": 38, "action": "pickup", "order_id": 17288, "point_id": 47288}, {"courier_id": 38, "action": "dropoff", "order_id": 17288, "point_id": 67288}, {"courier_id": 39, "action": "pickup", "order_id": 17289, "point_id": 47289}, {"courier_id": 39, "action": "dropoff", "order_id": 17289, "point_id": 67289}, {"courier_id": 40, "action": "pickup", "order_id": 17293, "point_id": 47293}, {"courier_id": 40, "action": "dropoff", "order_id": 17293, "point_id": 67293}, {"courier_id": 41, "action": "pickup", "order_id": 17295, "point_id": 47295}, {"courier_id": 41, "action": "dropoff", "order_id": 17295, "point_id": 67295}, {"courier_id": 213, "action": "pickup", "order_id": 16760, "point_id": 46760}, {"courier_id": 213, "action": "dropoff", "order_id": 16760, "point_id": 66760}, {"courier_id": 220, "action": "pickup", "order_id": 10716, "point_id": 40716}, {"courier_id": 220, "action": "dropoff", "order_id": 10716, "point_id": 60716}, {"courier_id": 42, "action": "pickup", "order_id": 17153, "point_id": 47153}, {"courier_id": 42, "action": "dropoff", "order_id": 17153, "point_id": 67153}, {"courier_id": 136, "action": "pickup", "order_id": 16878, "point_id": 46878}, {"courier_id": 136, "action": "dropoff", "order_id": 16878, "point_id": 66878}, {"courier_id": 244, "action": "pickup", "order_id": 13716, "point_id": 43716}, {"courier_id": 244, "action": "dropoff", "order_id": 13716, "point_id": 63716}, {"courier_id": 43, "action": "pickup", "order_id": 10631, "point_id": 40631}, {"courier_id": 43, "action": "dropoff", "order_id": 10631, "point_id": 60631}, {"courier_id": 266, "action": "pickup", "order_id": 17140, "point_id": 47140}, {"courier_id": 266, "action": "dropoff", "order_id": 17140, "point_id": 67140}, {"courier_id": 247, "action": "pickup", "order_id": 13757, "point_id": 43757}, {"courier_id": 247, "action": "dropoff", "order_id": 13757, "point_id": 63757}, {"courier_id": 56, "action": "pickup", "order_id": 17260, "point_id": 47260}, {"courier_id": 56, "action": "dropoff", "order_id": 17260, "point_id": 67260}, {"courier_id": 76, "action": "pickup", "order_id": 17185, "point_id": 47185}, {"courier_id": 76, "action": "dropoff", "order_id": 17185, "point_id": 67185}, {"courier_id": 122, "action": "pickup", "order_id": 17145, "point_id": 47145}, {"courier_id": 122, "action": "dropoff", "order_id": 17145, "point_id": 67145}, {"courier_id": 211, "action": "pickup", "order_id": 17199, "point_id": 47199}, {"courier_id": 211, "action": "dropoff", "order_id": 17199, "point_id": 67199}, {"courier_id": 67, "action": "pickup", "order_id": 16990, "point_id": 46990}, {"courier_id": 67, "action": "dropoff", "order_id": 16990, "point_id": 66990}, {"courier_id": 44, "action": "pickup", "order_id": 13677, "point_id": 43677}, {"courier_id": 44, "action": "dropoff", "order_id": 13677, "point_id": 63677}, {"courier_id": 45, "action": "pickup", "order_id": 13847, "point_id": 43847}, {"courier_id": 45, "action": "dropoff", "order_id": 13847, "point_id": 63847}, {"courier_id": 46, "action": "pickup", "order_id": 15844, "point_id": 45844}, {"courier_id": 46, "action": "dropoff", "order_id": 15844, "point_id": 65844}, {"courier_id": 47, "action": "pickup", "order_id": 16294, "point_id": 46294}, {"courier_id": 47, "action": "dropoff", "order_id": 16294, "point_id": 66294}, {"courier_id": 48, "action": "pickup", "order_id": 16369, "point_id": 46369}, {"courier_id": 48, "action": "dropoff", "order_id": 16369, "point_id": 66369}, {"courier_id": 49, "action": "pickup", "order_id": 16576, "point_id": 46576}, {"courier_id": 49, "action": "dropoff", "order_id": 16576, "point_id": 66576}, {"courier_id": 50, "action": "pickup", "order_id": 16578, "point_id": 46578}, {"courier_id": 50, "action": "dropoff", "order_id": 16578, "point_id": 66578}, {"courier_id": 51, "action": "pickup", "order_id": 17030, "point_id": 47030}, {"courier_id": 51, "action": "dropoff", "order_id": 17030, "point_id": 67030}, {"courier_id": 52, "action": "pickup", "order_id": 17204, "point_id": 47204}, {"courier_id": 52, "action": "dropoff", "order_id": 17204, "point_id": 67204}, {"courier_id": 53, "action": "pickup", "order_id": 17215, "point_id": 47215}, {"courier_id": 53, "action": "dropoff", "order_id": 17215, "point_id": 67215}, {"courier_id": 54, "action": "pickup", "order_id": 17256, "point_id": 47256}, {"courier_id": 54, "action": "dropoff", "order_id": 17256, "point_id": 67256}, {"courier_id": 55, "action": "pickup", "order_id": 17276, "point_id": 47276}, {"courier_id": 55, "action": "dropoff", "order_id": 17276, "point_id": 67276}, {"courier_id": 58, "action": "pickup", "order_id": 17299, "point_id": 47299}, {"courier_id": 58, "action": "dropoff", "order_id": 17299, "point_id": 67299}, {"courier_id": 59, "action": "pickup", "order_id": 17300, "point_id": 47300}, {"courier_id": 59, "action": "dropoff", "order_id": 17300, "point_id": 67300}, {"courier_id": 60, "action": "pickup", "order_id": 17301, "point_id": 47301}, {"courier_id": 60, "action": "dropoff", "order_id": 17301, "point_id": 67301}, {"courier_id": 65, "action": "pickup", "order_id": 10240, "point_id": 40240}, {"courier_id": 65, "action": "dropoff", "order_id": 10240, "point_id": 60240}, {"courier_id": 61, "action": "pickup", "order_id": 17297, "point_id": 47297}, {"courier_id": 61, "action": "dropoff", "order_id": 17297, "point_id": 67297}, {"courier_id": 62, "action": "pickup", "order_id": 17298, "point_id": 47298}, {"courier_id": 62, "action": "dropoff", "order_id": 17298, "point_id": 67298}, {"courier_id": 63, "action": "pickup", "order_id": 17296, "point_id": 47296}, {"courier_id": 63, "action": "dropoff", "order_id": 17296, "point_id": 67296}, {"courier_id": 131, "action": "pickup", "order_id": 13307, "point_id": 43307}, {"courier_id": 131, "action": "dropoff", "order_id": 13307, "point_id": 63307}, {"courier_id": 64, "action": "pickup", "order_id": 10613, "point_id": 40613}, {"courier_id": 64, "action": "dropoff", "order_id": 10613, "point_id": 60613}, {"courier_id": 144, "action": "pickup", "order_id": 12684, "point_id": 42684}, {"courier_id": 144, "action": "dropoff", "order_id": 12684, "point_id": 62684}, {"courier_id": 66, "action": "pickup", "order_id": 17294, "point_id": 47294}, {"courier_id": 66, "action": "dropoff", "order_id": 17294, "point_id": 67294}, {"courier_id": 160, "action": "pickup", "order_id": 15985, "point_id": 45985}, {"courier_id": 160, "action": "dropoff", "order_id": 15985, "point_id": 65985}, {"courier_id": 246, "action": "pickup", "order_id": 17088, "point_id": 47088}, {"courier_id": 246, "action": "dropoff", "order_id": 17088, "point_id": 67088}, {"courier_id": 68, "action": "pickup", "order_id": 17291, "point_id": 47291}, {"courier_id": 68, "action": "dropoff", "order_id": 17291, "point_id": 67291}, {"courier_id": 69, "action": "pickup", "order_id": 17290, "point_id": 47290}, {"courier_id": 69, "action": "dropoff", "order_id": 17290, "point_id": 67290}, {"courier_id": 70, "action": "pickup", "order_id": 17292, "point_id": 47292}, {"courier_id": 70, "action": "dropoff", "order_id": 17292, "point_id": 67292}, {"courier_id": 252, "action": "pickup", "order_id": 17035, "point_id": 47035}, {"courier_id": 252, "action": "dropoff", "order_id": 17035, "point_id": 67035}, {"courier_id": 71, "action": "pickup", "order_id": 10406, "point_id": 40406}, {"courier_id": 71, "action": "dropoff", "order_id": 10406, "point_id": 60406}, {"courier_id": 72, "action": "pickup", "order_id": 12052, "point_id": 42052}, {"courier_id": 72, "action": "dropoff", "order_id": 12052, "point_id": 62052}, {"courier_id": 73, "action": "pickup", "order_id": 13619, "point_id": 43619}, {"courier_id": 73, "action": "dropoff", "order_id": 13619, "point_id": 63619}, {"courier_id": 74, "action": "pickup", "order_id": 14050, "point_id": 44050}, {"courier_id": 74, "action": "dropoff", "order_id": 14050, "point_id": 64050}, {"courier_id": 75, "action": "pickup", "order_id": 14325, "point_id": 44325}, {"courier_id": 75, "action": "dropoff", "order_id": 14325, "point_id": 64325}, {"courier_id": 77, "action": "pickup", "order_id": 14393, "point_id": 44393}, {"courier_id": 77, "action": "dropoff", "order_id": 14393, "point_id": 64393}, {"courier_id": 78, "action": "pickup", "order_id": 14804, "point_id": 44804}, {"courier_id": 78, "action": "dropoff", "order_id": 14804, "point_id": 64804}, {"courier_id": 79, "action": "pickup", "order_id": 14907, "point_id": 44907}, {"courier_id": 79, "action": "dropoff", "order_id": 14907, "point_id": 64907}, {"courier_id": 80, "action": "pickup", "order_id": 14993, "point_id": 44993}, {"courier_id": 80, "action": "dropoff", "order_id": 14993, "point_id": 64993}, {"courier_id": 81, "action": "pickup", "order_id": 15091, "point_id": 45091}, {"courier_id": 81, "action": "dropoff", "order_id": 15091, "point_id": 65091}, {"courier_id": 82, "action": "pickup", "order_id": 15552, "point_id": 45552}, {"courier_id": 82, "action": "dropoff", "order_id": 15552, "point_id": 65552}, {"courier_id": 83, "action": "pickup", "order_id": 15575, "point_id": 45575}, {"courier_id": 83, "action": "dropoff", "order_id": 15575, "point_id": 65575}, {"courier_id": 84, "action": "pickup", "order_id": 15660, "point_id": 45660}, {"courier_id": 84, "action": "dropoff", "order_id": 15660, "point_id": 65660}, {"courier_id": 85, "action": "pickup", "order_id": 15839, "point_id": 45839}, {"courier_id": 85, "action": "dropoff", "order_id": 15839, "point_id": 65839}, {"courier_id": 86, "action": "pickup", "order_id": 16087, "point_id": 46087}, {"courier_id": 86, "action": "dropoff", "order_id": 16087, "point_id": 66087}, {"courier_id": 87, "action": "pickup", "order_id": 16567, "point_id": 46567}, {"courier_id": 87, "action": "dropoff", "order_id": 16567, "point_id": 66567}, {"courier_id": 88, "action": "pickup", "order_id": 16637, "point_id": 46637}, {"courier_id": 88, "action": "dropoff", "order_id": 16637, "point_id": 66637}, {"courier_id": 89, "action": "pickup", "order_id": 16957, "point_id": 46957}, {"courier_id": 89, "action": "dropoff", "order_id": 16957, "point_id": 66957}, {"courier_id": 90, "action": "pickup", "order_id": 17039, "point_id": 47039}, {"courier_id": 90, "action": "dropoff", "order_id": 17039, "point_id": 67039}, {"courier_id": 91, "action": "pickup", "order_id": 17060, "point_id": 47060}, {"courier_id": 91, "action": "dropoff", "order_id": 17060, "point_id": 67060}, {"courier_id": 92, "action": "pickup", "order_id": 17092, "point_id": 47092}, {"courier_id": 92, "action": "dropoff", "order_id": 17092, "point_id": 67092}, {"courier_id": 93, "action": "pickup", "order_id": 17113, "point_id": 47113}, {"courier_id": 93, "action": "dropoff", "order_id": 17113, "point_id": 67113}, {"courier_id": 94, "action": "pickup", "order_id": 17133, "point_id": 47133}, {"courier_id": 94, "action": "dropoff", "order_id": 17133, "point_id": 67133}, {"courier_id": 95, "action": "pickup", "order_id": 17161, "point_id": 47161}, {"courier_id": 95, "action": "dropoff", "order_id": 17161, "point_id": 67161}, {"courier_id": 96, "action": "pickup", "order_id": 17184, "point_id": 47184}, {"courier_id": 96, "action": "dropoff", "order_id": 17184, "point_id": 67184}, {"courier_id": 97, "action": "pickup", "order_id": 17187, "point_id": 47187}, {"courier_id": 97, "action": "dropoff", "order_id": 17187, "point_id": 67187}, {"courier_id": 98, "action": "pickup", "order_id": 17219, "point_id": 47219}, {"courier_id": 98, "action": "dropoff", "order_id": 17219, "point_id": 67219}, {"courier_id": 99, "action": "pickup", "order_id": 17233, "point_id": 47233}, {"courier_id": 99, "action": "dropoff", "order_id": 17233, "point_id": 67233}, {"courier_id": 100, "action": "pickup", "order_id": 17242, "point_id": 47242}, {"courier_id": 100, "action": "dropoff", "order_id": 17242, "point_id": 67242}, {"courier_id": 102, "action": "pickup", "order_id": 17250, "point_id": 47250}, {"courier_id": 102, "action": "dropoff", "order_id": 17250, "point_id": 67250}, {"courier_id": 103, "action": "pickup", "order_id": 17261, "point_id": 47261}, {"courier_id": 103, "action": "dropoff", "order_id": 17261, "point_id": 67261}, {"courier_id": 135, "action": "pickup", "order_id": 10450, "point_id": 40450}, {"courier_id": 135, "action": "dropoff", "order_id": 10450, "point_id": 60450}, {"courier_id": 150, "action": "pickup", "order_id": 17046, "point_id": 47046}, {"courier_id": 150, "action": "dropoff", "order_id": 17046, "point_id": 67046}, {"courier_id": 217, "action": "pickup", "order_id": 17054, "point_id": 47054}, {"courier_id": 217, "action": "dropoff", "order_id": 17054, "point_id": 67054}, {"courier_id": 232, "action": "pickup", "order_id": 17104, "point_id": 47104}, {"courier_id": 232, "action": "dropoff", "order_id": 17104, "point_id": 67104}, {"courier_id": 198, "action": "pickup", "order_id": 16979, "point_id": 46979}, {"courier_id": 198, "action": "dropoff", "order_id": 16979, "point_id": 66979}, {"courier_id": 104, "action": "pickup", "order_id": 17287, "point_id": 47287}, {"courier_id": 104, "action": "dropoff", "order_id": 17287, "point_id": 67287}, {"courier_id": 147, "action": "pickup", "order_id": 17074, "point_id": 47074}, {"courier_id": 147, "action": "dropoff", "order_id": 17074, "point_id": 67074}, {"courier_id": 164, "action": "pickup", "order_id": 16664, "point_id": 46664}, {"courier_id": 164, "action": "dropoff", "order_id": 16664, "point_id": 66664}, {"courier_id": 130, "action": "pickup", "order_id": 13373, "point_id": 43373}, {"courier_id": 130, "action": "dropoff", "order_id": 13373, "point_id": 63373}, {"courier_id": 153, "action": "pickup", "order_id": 15272, "point_id": 45272}, {"courier_id": 153, "action": "dropoff", "order_id": 15272, "point_id": 65272}, {"courier_id": 105, "action": "pickup", "order_id": 17286, "point_id": 47286}, {"courier_id": 105, "action": "dropoff", "order_id": 17286, "point_id": 67286}, {"courier_id": 263, "action": "pickup", "order_id": 12229, "point_id": 42229}, {"courier_id": 263, "action": "dropoff", "order_id": 12229, "point_id": 62229}, {"courier_id": 106, "action": "pickup", "order_id": 17283, "point_id": 47283}, {"courier_id": 106, "action": "dropoff", "order_id": 17283, "point_id": 67283}, {"courier_id": 107, "action": "pickup", "order_id": 17284, "point_id": 47284}, {"courier_id": 107, "action": "dropoff", "order_id": 17284, "point_id": 67284}, {"courier_id": 108, "action": "pickup", "order_id": 17285, "point_id": 47285}, {"courier_id": 108, "action": "dropoff", "order_id": 17285, "point_id": 67285}, {"courier_id": 113, "action": "pickup", "order_id": 14881, "point_id": 44881}, {"courier_id": 113, "action": "dropoff", "order_id": 14881, "point_id": 64881}, {"courier_id": 120, "action": "pickup", "order_id": 16936, "point_id": 46936}, {"courier_id": 120, "action": "dropoff", "order_id": 16936, "point_id": 66936}, {"courier_id": 166, "action": "pickup", "order_id": 16984, "point_id": 46984}, {"courier_id": 166, "action": "dropoff", "order_id": 16984, "point_id": 66984}, {"courier_id": 168, "action": "pickup", "order_id": 17089, "point_id": 47089}, {"courier_id": 168, "action": "dropoff", "order_id": 17089, "point_id": 67089}, {"courier_id": 109, "action": "pickup", "order_id": 17282, "point_id": 47282}, {"courier_id": 109, "action": "dropoff", "order_id": 17282, "point_id": 67282}, {"courier_id": 110, "action": "pickup", "order_id": 17281, "point_id": 47281}, {"courier_id": 110, "action": "dropoff", "order_id": 17281, "point_id": 67281}, {"courier_id": 119, "action": "pickup", "order_id": 10618, "point_id": 40618}, {"courier_id": 119, "action": "dropoff", "order_id": 10618, "point_id": 60618}, {"courier_id": 286, "action": "pickup", "order_id": 15326, "point_id": 45326}, {"courier_id": 286, "action": "dropoff", "order_id": 15326, "point_id": 65326}, {"courier_id": 111, "action": "pickup", "order_id": 17279, "point_id": 47279}, {"courier_id": 111, "action": "dropoff", "order_id": 17279, "point_id": 67279}, {"courier_id": 112, "action": "pickup", "order_id": 17278, "point_id": 47278}, {"courier_id": 112, "action": "dropoff", "order_id": 17278, "point_id": 67278}, {"courier_id": 174, "action": "pickup", "order_id": 16535, "point_id": 46535}, {"courier_id": 174, "action": "dropoff", "order_id": 16535, "point_id": 66535}, {"courier_id": 225, "action": "pickup", "order_id": 17136, "point_id": 47136}, {"courier_id": 225, "action": "dropoff", "order_id": 17136, "point_id": 67136}, {"courier_id": 265, "action": "pickup", "order_id": 15011, "point_id": 45011}, {"courier_id": 265, "action": "dropoff", "order_id": 15011, "point_id": 65011}, {"courier_id": 114, "action": "pickup", "order_id": 17274, "point_id": 47274}, {"courier_id": 114, "action": "dropoff", "order_id": 17274, "point_id": 67274}, {"courier_id": 260, "action": "pickup", "order_id": 14021, "point_id": 44021}, {"courier_id": 260, "action": "dropoff", "order_id": 14021, "point_id": 64021}, {"courier_id": 115, "action": "pickup", "order_id": 17268, "point_id": 47268}, {"courier_id": 115, "action": "dropoff", "order_id": 17268, "point_id": 67268}, {"courier_id": 117, "action": "pickup", "order_id": 17271, "point_id": 47271}, {"courier_id": 117, "action": "dropoff", "order_id": 17271, "point_id": 67271}, {"courier_id": 118, "action": "pickup", "order_id": 17272, "point_id": 47272}, {"courier_id": 118, "action": "dropoff", "order_id": 17272, "point_id": 67272}, {"courier_id": 121, "action": "pickup", "order_id": 17270, "point_id": 47270}, {"courier_id": 121, "action": "dropoff", "order_id": 17270, "point_id": 67270}, {"courier_id": 161, "action": "pickup", "order_id": 10600, "point_id": 40600}, {"courier_id": 161, "action": "dropoff", "order_id": 10600, "point_id": 60600}, {"courier_id": 257, "action": "pickup", "order_id": 17141, "point_id": 47141}, {"courier_id": 257, "action": "dropoff", "order_id": 17141, "point_id": 67141}, {"courier_id": 123, "action": "pickup", "order_id": 17265, "point_id": 47265}, {"courier_id": 123, "action": "dropoff", "order_id": 17265, "point_id": 67265}, {"courier_id": 124, "action": "pickup", "order_id": 17267, "point_id": 47267}, {"courier_id": 124, "action": "dropoff", "order_id": 17267, "point_id": 67267}, {"courier_id": 125, "action": "pickup", "order_id": 17266, "point_id": 47266}, {"courier_id": 125, "action": "dropoff", "order_id": 17266, "point_id": 67266}, {"courier_id": 268, "action": "pickup", "order_id": 10669, "point_id": 40669}, {"courier_id": 268, "action": "dropoff", "order_id": 10669, "point_id": 60669}, {"courier_id": 126, "action": "pickup", "order_id": 17264, "point_id": 47264}, {"courier_id": 126, "action": "dropoff", "order_id": 17264, "point_id": 67264}, {"courier_id": 127, "action": "pickup", "order_id": 10003, "point_id": 40003}, {"courier_id": 127, "action": "dropoff", "order_id": 10003, "point_id": 60003}, {"courier_id": 128, "action": "pickup", "order_id": 10856, "point_id": 40856}, {"courier_id": 128, "action": "dropoff", "order_id": 10856, "point_id": 60856}, {"courier_id": 129, "action": "pickup", "order_id": 12804, "point_id": 42804}, {"courier_id": 129, "action": "dropoff", "order_id": 12804, "point_id": 62804}, {"courier_id": 132, "action": "pickup", "order_id": 14738, "point_id": 44738}, {"courier_id": 132, "action": "dropoff", "order_id": 14738, "point_id": 64738}, {"courier_id": 133, "action": "pickup", "order_id": 15722, "point_id": 45722}, {"courier_id": 133, "action": "dropoff", "order_id": 15722, "point_id": 65722}, {"courier_id": 137, "action": "pickup", "order_id": 16133, "point_id": 46133}, {"courier_id": 137, "action": "dropoff", "order_id": 16133, "point_id": 66133}, {"courier_id": 138, "action": "pickup", "order_id": 16321, "point_id": 46321}, {"courier_id": 138, "action": "dropoff", "order_id": 16321, "point_id": 66321}, {"courier_id": 139, "action": "pickup", "order_id": 16695, "point_id": 46695}, {"courier_id": 139, "action": "dropoff", "order_id": 16695, "point_id": 66695}, {"courier_id": 140, "action": "pickup", "order_id": 16748, "point_id": 46748}, {"courier_id": 140, "action": "dropoff", "order_id": 16748, "point_id": 66748}, {"courier_id": 141, "action": "pickup", "order_id": 16839, "point_id": 46839}, {"courier_id": 141, "action": "dropoff", "order_id": 16839, "point_id": 66839}, {"courier_id": 142, "action": "pickup", "order_id": 16910, "point_id": 46910}, {"courier_id": 142, "action": "dropoff", "order_id": 16910, "point_id": 66910}, {"courier_id": 145, "action": "pickup", "order_id": 16976, "point_id": 46976}, {"courier_id": 145, "action": "dropoff", "order_id": 16976, "point_id": 66976}, {"courier_id": 146, "action": "pickup", "order_id": 17071, "point_id": 47071}, {"courier_id": 146, "action": "dropoff", "order_id": 17071, "point_id": 67071}, {"courier_id": 148, "action": "pickup", "order_id": 17096, "point_id": 47096}, {"courier_id": 148, "action": "dropoff", "order_id": 17096, "point_id": 67096}, {"courier_id": 149, "action": "pickup", "order_id": 17152, "point_id": 47152}, {"courier_id": 149, "action": "dropoff", "order_id": 17152, "point_id": 67152}, {"courier_id": 151, "action": "pickup", "order_id": 17160, "point_id": 47160}, {"courier_id": 151, "action": "dropoff", "order_id": 17160, "point_id": 67160}, {"courier_id": 152, "action": "pickup", "order_id": 17164, "point_id": 47164}, {"courier_id": 152, "action": "dropoff", "order_id": 17164, "point_id": 67164}, {"courier_id": 154, "action": "pickup", "order_id": 17177, "point_id": 47177}, {"courier_id": 154, "action": "dropoff", "order_id": 17177, "point_id": 67177}, {"courier_id": 155, "action": "pickup", "order_id": 17178, "point_id": 47178}, {"courier_id": 155, "action": "dropoff", "order_id": 17178, "point_id": 67178}, {"courier_id": 156, "action": "pickup", "order_id": 17210, "point_id": 47210}, {"courier_id": 156, "action": "dropoff", "order_id": 17210, "point_id": 67210}, {"courier_id": 157, "action": "pickup", "order_id": 17213, "point_id": 47213}, {"courier_id": 157, "action": "dropoff", "order_id": 17213, "point_id": 67213}, {"courier_id": 158, "action": "pickup", "order_id": 17216, "point_id": 47216}, {"courier_id": 158, "action": "dropoff", "order_id": 17216, "point_id": 67216}, {"courier_id": 159, "action": "pickup", "order_id": 17263, "point_id": 47263}, {"courier_id": 159, "action": "dropoff", "order_id": 17263, "point_id": 67263}, {"courier_id": 190, "action": "pickup", "order_id": 15352, "point_id": 45352}, {"courier_id": 190, "action": "dropoff", "order_id": 15352, "point_id": 65352}, {"courier_id": 162, "action": "pickup", "order_id": 17245, "point_id": 47245}, {"courier_id": 162, "action": "dropoff", "order_id": 17245, "point_id": 67245}, {"courier_id": 163, "action": "pickup", "order_id": 17259, "point_id": 47259}, {"courier_id": 163, "action": "dropoff", "order_id": 17259, "point_id": 67259}, {"courier_id": 165, "action": "pickup", "order_id": 17262, "point_id": 47262}, {"courier_id": 165, "action": "dropoff", "order_id": 17262, "point_id": 67262}, {"courier_id": 239, "action": "pickup", "order_id": 14174, "point_id": 44174}, {"courier_id": 239, "action": "dropoff", "order_id": 14174, "point_id": 64174}, {"courier_id": 179, "action": "pickup", "order_id": 16791, "point_id": 46791}, {"courier_id": 179, "action": "dropoff", "order_id": 16791, "point_id": 66791}, {"courier_id": 272, "action": "pickup", "order_id": 16872, "point_id": 46872}, {"courier_id": 272, "action": "dropoff", "order_id": 16872, "point_id": 66872}, {"courier_id": 167, "action": "pickup", "order_id": 17257, "point_id": 47257}, {"courier_id": 167, "action": "dropoff", "order_id": 17257, "point_id": 67257}, {"courier_id": 237, "action": "pickup", "order_id": 17019, "point_id": 47019}, {"courier_id": 237, "action": "dropoff", "order_id": 17019, "point_id": 67019}, {"courier_id": 227, "action": "pickup", "order_id": 17045, "point_id": 47045}, {"courier_id": 227, "action": "dropoff", "order_id": 17045, "point_id": 67045}, {"courier_id": 169, "action": "pickup", "order_id": 17255, "point_id": 47255}, {"courier_id": 169, "action": "dropoff", "order_id": 17255, "point_id": 67255}, {"courier_id": 170, "action": "pickup", "order_id": 17251, "point_id": 47251}, {"courier_id": 170, "action": "dropoff", "order_id": 17251, "point_id": 67251}, {"courier_id": 171, "action": "pickup", "order_id": 17253, "point_id": 47253}, {"courier_id": 171, "action": "dropoff", "order_id": 17253, "point_id": 67253}, {"courier_id": 173, "action": "pickup", "order_id": 17252, "point_id": 47252}, {"courier_id": 173, "action": "dropoff", "order_id": 17252, "point_id": 67252}, {"courier_id": 175, "action": "pickup", "order_id": 17247, "point_id": 47247}, {"courier_id": 175, "action": "dropoff", "order_id": 17247, "point_id": 67247}, {"courier_id": 176, "action": "pickup", "order_id": 17243, "point_id": 47243}, {"courier_id": 176, "action": "dropoff", "order_id": 17243, "point_id": 67243}, {"courier_id": 177, "action": "pickup", "order_id": 17246, "point_id": 47246}, {"courier_id": 177, "action": "dropoff", "order_id": 17246, "point_id": 67246}, {"courier_id": 251, "action": "pickup", "order_id": 17050, "point_id": 47050}, {"courier_id": 251, "action": "dropoff", "order_id": 17050, "point_id": 67050}, {"courier_id": 178, "action": "pickup", "order_id": 17218, "point_id": 47218}, {"courier_id": 178, "action": "dropoff", "order_id": 17218, "point_id": 67218}, {"courier_id": 180, "action": "pickup", "order_id": 17241, "point_id": 47241}, {"courier_id": 180, "action": "dropoff", "order_id": 17241, "point_id": 67241}, {"courier_id": 181, "action": "pickup", "order_id": 17240, "point_id": 47240}, {"courier_id": 181, "action": "dropoff", "order_id": 17240, "point_id": 67240}, {"courier_id": 182, "action": "pickup", "order_id": 17235, "point_id": 47235}, {"courier_id": 182, "action": "dropoff", "order_id": 17235, "point_id": 67235}, {"courier_id": 183, "action": "pickup", "order_id": 17238, "point_id": 47238}, {"courier_id": 183, "action": "dropoff", "order_id": 17238, "point_id": 67238}, {"courier_id": 184, "action": "pickup", "order_id": 17237, "point_id": 47237}, {"courier_id": 184, "action": "dropoff", "order_id": 17237, "point_id": 67237}, {"courier_id": 186, "action": "pickup", "order_id": 17236, "point_id": 47236}, {"courier_id": 186, "action": "dropoff", "order_id": 17236, "point_id": 67236}, {"courier_id": 187, "action": "pickup", "order_id": 17094, "point_id": 47094}, {"courier_id": 187, "action": "dropoff", "order_id": 17094, "point_id": 67094}, {"courier_id": 188, "action": "pickup", "order_id": 17232, "point_id": 47232}, {"courier_id": 188, "action": "dropoff", "order_id": 17232, "point_id": 67232}, {"courier_id": 189, "action": "pickup", "order_id": 10101, "point_id": 40101}, {"courier_id": 189, "action": "dropoff", "order_id": 10101, "point_id": 60101}, {"courier_id": 191, "action": "pickup", "order_id": 10288, "point_id": 40288}, {"courier_id": 191, "action": "dropoff", "order_id": 10288, "point_id": 60288}, {"courier_id": 192, "action": "pickup", "order_id": 10310, "point_id": 40310}, {"courier_id": 192, "action": "dropoff", "order_id": 10310, "point_id": 60310}, {"courier_id": 193, "action": "pickup", "order_id": 10341, "point_id": 40341}, {"courier_id": 193, "action": "dropoff", "order_id": 10341, "point_id": 60341}, {"courier_id": 194, "action": "pickup", "order_id": 10345, "point_id": 40345}, {"courier_id": 194, "action": "dropoff", "order_id": 10345, "point_id": 60345}, {"courier_id": 195, "action": "pickup", "order_id": 10396, "point_id": 40396}, {"courier_id": 195, "action": "dropoff", "order_id": 10396, "point_id": 60396}, {"courier_id": 196, "action": "pickup", "order_id": 10414, "point_id": 40414}, {"courier_id": 196, "action": "dropoff", "order_id": 10414, "point_id": 60414}, {"courier_id": 197, "action": "pickup", "order_id": 10542, "point_id": 40542}, {"courier_id": 197, "action": "dropoff", "order_id": 10542, "point_id": 60542}, {"courier_id": 199, "action": "pickup", "order_id": 10648, "point_id": 40648}, {"courier_id": 199, "action": "dropoff", "order_id": 10648, "point_id": 60648}, {"courier_id": 200, "action": "pickup", "order_id": 11110, "point_id": 41110}, {"courier_id": 200, "action": "dropoff", "order_id": 11110, "point_id": 61110}, {"courier_id": 201, "action": "pickup", "order_id": 10227, "point_id": 40227}, {"courier_id": 201, "action": "dropoff", "order_id": 10227, "point_id": 60227}, {"courier_id": 202, "action": "pickup", "order_id": 11947, "point_id": 41947}, {"courier_id": 202, "action": "dropoff", "order_id": 11947, "point_id": 61947}, {"courier_id": 203, "action": "pickup", "order_id": 11951, "point_id": 41951}, {"courier_id": 203, "action": "dropoff", "order_id": 11951, "point_id": 61951}, {"courier_id": 204, "action": "pickup", "order_id": 12006, "point_id": 42006}, {"courier_id": 204, "action": "dropoff", "order_id": 12006, "point_id": 62006}, {"courier_id": 205, "action": "pickup", "order_id": 12217, "point_id": 42217}, {"courier_id": 205, "action": "dropoff", "order_id": 12217, "point_id": 62217}, {"courier_id": 206, "action": "pickup", "order_id": 12355, "point_id": 42355}, {"courier_id": 206, "action": "dropoff", "order_id": 12355, "point_id": 62355}, {"courier_id": 207, "action": "pickup", "order_id": 12410, "point_id": 42410}, {"courier_id": 207, "action": "dropoff", "order_id": 12410, "point_id": 62410}, {"courier_id": 208, "action": "pickup", "order_id": 12841, "point_id": 42841}, {"courier_id": 208, "action": "dropoff", "order_id": 12841, "point_id": 62841}, {"courier_id": 209, "action": "pickup", "order_id": 12861, "point_id": 42861}, {"courier_id": 209, "action": "dropoff", "order_id": 12861, "point_id": 62861}, {"courier_id": 210, "action": "pickup", "order_id": 13083, "point_id": 43083}, {"courier_id": 210, "action": "dropoff", "order_id": 13083, "point_id": 63083}, {"courier_id": 212, "action": "pickup", "order_id": 13128, "point_id": 43128}, {"courier_id": 212, "action": "dropoff", "order_id": 13128, "point_id": 63128}, {"courier_id": 214, "action": "pickup", "order_id": 13550, "point_id": 43550}, {"courier_id": 214, "action": "dropoff", "order_id": 13550, "point_id": 63550}, {"courier_id": 215, "action": "pickup", "order_id": 13653, "point_id": 43653}, {"courier_id": 215, "action": "dropoff", "order_id": 13653, "point_id": 63653}, {"courier_id": 216, "action": "pickup", "order_id": 13935, "point_id": 43935}, {"courier_id": 216, "action": "dropoff", "order_id": 13935, "point_id": 63935}, {"courier_id": 218, "action": "pickup", "order_id": 13961, "point_id": 43961}, {"courier_id": 218, "action": "dropoff", "order_id": 13961, "point_id": 63961}, {"courier_id": 219, "action": "pickup", "order_id": 14196, "point_id": 44196}, {"courier_id": 219, "action": "dropoff", "order_id": 14196, "point_id": 64196}, {"courier_id": 221, "action": "pickup", "order_id": 14571, "point_id": 44571}, {"courier_id": 221, "action": "dropoff", "order_id": 14571, "point_id": 64571}, {"courier_id": 222, "action": "pickup", "order_id": 15040, "point_id": 45040}, {"courier_id": 222, "action": "dropoff", "order_id": 15040, "point_id": 65040}, {"courier_id": 223, "action": "pickup", "order_id": 15156, "point_id": 45156}, {"courier_id": 223, "action": "dropoff", "order_id": 15156, "point_id": 65156}, {"courier_id": 224, "action": "pickup", "order_id": 15348, "point_id": 45348}, {"courier_id": 224, "action": "dropoff", "order_id": 15348, "point_id": 65348}, {"courier_id": 226, "action": "pickup", "order_id": 15415, "point_id": 45415}, {"courier_id": 226, "action": "dropoff", "order_id": 15415, "point_id": 65415}, {"courier_id": 228, "action": "pickup", "order_id": 15738, "point_id": 45738}, {"courier_id": 228, "action": "dropoff", "order_id": 15738, "point_id": 65738}, {"courier_id": 229, "action": "pickup", "order_id": 15842, "point_id": 45842}, {"courier_id": 229, "action": "dropoff", "order_id": 15842, "point_id": 65842}, {"courier_id": 230, "action": "pickup", "order_id": 15849, "point_id": 45849}, {"courier_id": 230, "action": "dropoff", "order_id": 15849, "point_id": 65849}, {"courier_id": 231, "action": "pickup", "order_id": 15858, "point_id": 45858}, {"courier_id": 231, "action": "dropoff", "order_id": 15858, "point_id": 65858}, {"courier_id": 234, "action": "pickup", "order_id": 15890, "point_id": 45890}, {"courier_id": 234, "action": "dropoff", "order_id": 15890, "point_id": 65890}, {"courier_id": 235, "action": "pickup", "order_id": 15891, "point_id": 45891}, {"courier_id": 235, "action": "dropoff", "order_id": 15891, "point_id": 65891}, {"courier_id": 236, "action": "pickup", "order_id": 10895, "point_id": 40895}, {"courier_id": 236, "action": "dropoff", "order_id": 10895, "point_id": 60895}, {"courier_id": 238, "action": "pickup", "order_id": 16058, "point_id": 46058}, {"courier_id": 238, "action": "dropoff", "order_id": 16058, "point_id": 66058}, {"courier_id": 240, "action": "pickup", "order_id": 16060, "point_id": 46060}, {"courier_id": 240, "action": "dropoff", "order_id": 16060, "point_id": 66060}, {"courier_id": 241, "action": "pickup", "order_id": 16168, "point_id": 46168}, {"courier_id": 241, "action": "dropoff", "order_id": 16168, "point_id": 66168}, {"courier_id": 242, "action": "pickup", "order_id": 16170, "point_id": 46170}, {"courier_id": 242, "action": "dropoff", "order_id": 16170, "point_id": 66170}, {"courier_id": 243, "action": "pickup", "order_id": 16232, "point_id": 46232}, {"courier_id": 243, "action": "dropoff", "order_id": 16232, "point_id": 66232}, {"courier_id": 245, "action": "pickup", "order_id": 16303, "point_id": 46303}, {"courier_id": 245, "action": "dropoff", "order_id": 16303, "point_id": 66303}, {"courier_id": 248, "action": "pickup", "order_id": 16306, "point_id": 46306}, {"courier_id": 248, "action": "dropoff", "order_id": 16306, "point_id": 66306}, {"courier_id": 249, "action": "pickup", "order_id": 16349, "point_id": 46349}, {"courier_id": 249, "action": "dropoff", "order_id": 16349, "point_id": 66349}, {"courier_id": 250, "action": "pickup", "order_id": 16353, "point_id": 46353}, {"courier_id": 250, "action": "dropoff", "order_id": 16353, "point_id": 66353}, {"courier_id": 253, "action": "pickup", "order_id": 16375, "point_id": 46375}, {"courier_id": 253, "action": "dropoff", "order_id": 16375, "point_id": 66375}, {"courier_id": 254, "action": "pickup", "order_id": 16401, "point_id": 46401}, {"courier_id": 254, "action": "dropoff", "order_id": 16401, "point_id": 66401}, {"courier_id": 255, "action": "pickup", "order_id": 16450, "point_id": 46450}, {"courier_id": 255, "action": "dropoff", "order_id": 16450, "point_id": 66450}, {"courier_id": 258, "action": "pickup", "order_id": 16484, "point_id": 46484}, {"courier_id": 258, "action": "dropoff", "order_id": 16484, "point_id": 66484}, {"courier_id": 259, "action": "pickup", "order_id": 16521, "point_id": 46521}, {"courier_id": 259, "action": "dropoff", "order_id": 16521, "point_id": 66521}, {"courier_id": 261, "action": "pickup", "order_id": 16522, "point_id": 46522}, {"courier_id": 261, "action": "dropoff", "order_id": 16522, "point_id": 66522}, {"courier_id": 262, "action": "pickup", "order_id": 16523, "point_id": 46523}, {"courier_id": 262, "action": "dropoff", "order_id": 16523, "point_id": 66523}, {"courier_id": 264, "action": "pickup", "order_id": 16559, "point_id": 46559}, {"courier_id": 264, "action": "dropoff", "order_id": 16559, "point_id": 66559}, {"courier_id": 267, "action": "pickup", "order_id": 16584, "point_id": 46584}, {"courier_id": 267, "action": "dropoff", "order_id": 16584, "point_id": 66584}, {"courier_id": 269, "action": "pickup", "order_id": 16590, "point_id": 46590}, {"courier_id": 269, "action": "dropoff", "order_id": 16590, "point_id": 66590}, {"courier_id": 270, "action": "pickup", "order_id": 16593, "point_id": 46593}, {"courier_id": 270, "action": "dropoff", "order_id": 16593, "point_id": 66593}, {"courier_id": 271, "action": "pickup", "order_id": 16606, "point_id": 46606}, {"courier_id": 271, "action": "dropoff", "order_id": 16606, "point_id": 66606}, {"courier_id": 273, "action": "pickup", "order_id": 16617, "point_id": 46617}, {"courier_id": 273, "action": "dropoff", "order_id": 16617, "point_id": 66617}, {"courier_id": 274, "action": "pickup", "order_id": 16683, "point_id": 46683}, {"courier_id": 274, "action": "dropoff", "order_id": 16683, "point_id": 66683}, {"courier_id": 275, "action": "pickup", "order_id": 16685, "point_id": 46685}, {"courier_id": 275, "action": "dropoff", "order_id": 16685, "point_id": 66685}, {"courier_id": 276, "action": "pickup", "order_id": 16761, "point_id": 46761}, {"courier_id": 276, "action": "dropoff", "order_id": 16761, "point_id": 66761}, {"courier_id": 277, "action": "pickup", "order_id": 16765, "point_id": 46765}, {"courier_id": 277, "action": "dropoff", "order_id": 16765, "point_id": 66765}, {"courier_id": 278, "action": "pickup", "order_id": 16785, "point_id": 46785}, {"courier_id": 278, "action": "dropoff", "order_id": 16785, "point_id": 66785}, {"courier_id": 279, "action": "pickup", "order_id": 16788, "point_id": 46788}, {"courier_id": 279, "action": "dropoff", "order_id": 16788, "point_id": 66788}, {"courier_id": 280, "action": "pickup", "order_id": 16789, "point_id": 46789}, {"courier_id": 280, "action": "dropoff", "order_id": 16789, "point_id": 66789}, {"courier_id": 281, "action": "pickup", "order_id": 16790, "point_id": 46790}, {"courier_id": 281, "action": "dropoff", "order_id": 16790, "point_id": 66790}, {"courier_id": 282, "action": "pickup", "order_id": 16819, "point_id": 46819}, {"courier_id": 282, "action": "dropoff", "order_id": 16819, "point_id": 66819}, {"courier_id": 283, "action": "pickup", "order_id": 16844, "point_id": 46844}, {"courier_id": 283, "action": "dropoff", "order_id": 16844, "point_id": 66844}, {"courier_id": 284, "action": "pickup", "order_id": 16845, "point_id": 46845}, {"courier_id": 284, "action": "dropoff", "order_id": 16845, "point_id": 66845}, {"courier_id": 285, "action": "pickup", "order_id": 16847, "point_id": 46847}, {"courier_id": 285, "action": "dropoff", "order_id": 16847, "point_id": 66847}, {"courier_id": 287, "action": "pickup", "order_id": 16849, "point_id": 46849}, {"courier_id": 287, "action": "dropoff", "order_id": 16849, "point_id": 66849}, {"courier_id": 288, "action": "pickup", "order_id": 16859, "point_id": 46859}, {"courier_id": 288, "action": "dropoff", "order_id": 16859, "point_id": 66859}, {"courier_id": 289, "action": "pickup", "order_id": 16863, "point_id": 46863}, {"courier_id": 289, "action": "dropoff", "order_id": 16863, "point_id": 66863}, {"courier_id": 290, "action": "pickup", "order_id": 16865, "point_id": 46865}, {"courier_id": 290, "action": "dropoff", "order_id": 16865, "point_id": 66865}, {"courier_id": 291, "action": "pickup", "order_id": 16889, "point_id": 46889}, {"courier_id": 291, "action": "dropoff", "order_id": 16889, "point_id": 66889}, {"courier_id": 292, "action": "pickup", "order_id": 16890, "point_id": 46890}, {"courier_id": 292, "action": "dropoff", "order_id": 16890, "point_id": 66890}, {"courier_id": 293, "action": "pickup", "order_id": 16891, "point_id": 46891}, {"courier_id": 293, "action": "dropoff", "order_id": 16891, "point_id": 66891}, {"courier_id": 294, "action": "pickup", "order_id": 16895, "point_id": 46895}, {"courier_id": 294, "action": "dropoff", "order_id": 16895, "point_id": 66895}, {"courier_id": 295, "action": "pickup", "order_id": 16909, "point_id": 46909}, {"courier_id": 295, "action": "dropoff", "order_id": 16909, "point_id": 66909}, {"courier_id": 296, "action": "pickup", "order_id": 16913, "point_id": 46913}, {"courier_id": 296, "action": "dropoff", "order_id": 16913, "point_id": 66913}, {"courier_id": 297, "action": "pickup", "order_id": 16914, "point_id": 46914}, {"courier_id": 297, "action": "dropoff", "order_id": 16914, "point_id": 66914}, {"courier_id": 298, "action": "pickup", "order_id": 16935, "point_id": 46935}, {"courier_id": 298, "action": "dropoff", "order_id": 16935, "point_id": 66935}, {"courier_id": 299, "action": "pickup", "order_id": 16950, "point_id": 46950}, {"courier_id": 299, "action": "dropoff", "order_id": 16950, "point_id": 66950}, {"courier_id": 300, "action": "pickup", "order_id": 16951, "point_id": 46951}, {"courier_id": 300, "action": "dropoff", "order_id": 16951, "point_id": 66951}, {"courier_id": 291, "action": "pickup", "order_id": 13380, "point_id": 43380}, {"courier_id": 291, "action": "dropoff", "order_id": 13380, "point_id": 63380}, {"courier_id": 219, "action": "pickup", "order_id": 17190, "point_id": 47190}, {"courier_id": 219, "action": "dropoff", "order_id": 17190, "point_id": 67190}, {"courier_id": 216, "action": "pickup", "order_id": 14487, "point_id": 44487}, {"courier_id": 216, "action": "dropoff", "order_id": 14487, "point_id": 64487}, {"courier_id": 222, "action": "pickup", "order_id": 17147, "point_id": 47147}, {"courier_id": 222, "action": "dropoff", "order_id": 17147, "point_id": 67147}, {"courier_id": 258, "action": "pickup", "order_id": 16620, "point_id": 46620}, {"courier_id": 258, "action": "dropoff", "order_id": 16620, "point_id": 66620}, {"courier_id": 271, "action": "pickup", "order_id": 17061, "point_id": 47061}, {"courier_id": 271, "action": "dropoff", "order_id": 17061, "point_id": 67061}, {"courier_id": 278, "action": "pickup", "order_id": 17003, "point_id": 47003}, {"courier_id": 278, "action": "dropoff", "order_id": 17003, "point_id": 67003}, {"courier_id": 223, "action": "pickup", "order_id": 17081, "point_id": 47081}, {"courier_id": 223, "action": "dropoff", "order_id": 17081, "point_id": 67081}, {"courier_id": 285, "action": "pickup", "order_id": 17118, "point_id": 47118}, {"courier_id": 285, "action": "dropoff", "order_id": 17118, "point_id": 67118}, {"courier_id": 261, "action": "pickup", "order_id": 16952, "point_id": 46952}, {"courier_id": 261, "action": "dropoff", "order_id": 16952, "point_id": 66952}, {"courier_id": 205, "action": "pickup", "order_id": 17106, "point_id": 47106}, {"courier_id": 205, "action": "dropoff", "order_id": 17106, "point_id": 67106}, {"courier_id": 206, "action": "pickup", "order_id": 17105, "point_id": 47105}, {"courier_id": 206, "action": "dropoff", "order_id": 17105, "point_id": 67105}, {"courier_id": 289, "action": "pickup", "order_id": 17080, "point_id": 47080}, {"courier_id": 289, "action": "dropoff", "order_id": 17080, "point_id": 67080}, {"courier_id": 203, "action": "pickup", "order_id": 16871, "point_id": 46871}, {"courier_id": 203, "action": "dropoff", "order_id": 16871, "point_id": 66871}, {"courier_id": 259, "action": "pickup", "order_id": 16953, "point_id": 46953}, {"courier_id": 259, "action": "dropoff", "order_id": 16953, "point_id": 66953}, {"courier_id": 283, "action": "pickup", "order_id": 17058, "point_id": 47058}, {"courier_id": 283, "action": "dropoff", "order_id": 17058, "point_id": 67058}, {"courier_id": 234, "action": "pickup", "order_id": 17004, "point_id": 47004}, {"courier_id": 234, "action": "dropoff", "order_id": 17004, "point_id": 67004}, {"courier_id": 279, "action": "pickup", "order_id": 17079, "point_id": 47079}, {"courier_id": 279, "action": "dropoff", "order_id": 17079, "point_id": 67079}, {"courier_id": 188, "action": "pickup", "order_id": 17083, "point_id": 47083}, {"courier_id": 188, "action": "dropoff", "order_id": 17083, "point_id": 67083}, {"courier_id": 218, "action": "pickup", "order_id": 17117, "point_id": 47117}, {"courier_id": 218, "action": "dropoff", "order_id": 17117, "point_id": 67117}, {"courier_id": 184, "action": "pickup", "order_id": 17082, "point_id": 47082}, {"courier_id": 184, "action": "dropoff", "order_id": 17082, "point_id": 67082}, {"courier_id": 221, "action": "pickup", "order_id": 17042, "point_id": 47042}, {"courier_id": 221, "action": "dropoff", "order_id": 17042, "point_id": 67042}, {"courier_id": 275, "action": "pickup", "order_id": 17085, "point_id": 47085}, {"courier_id": 275, "action": "dropoff", "order_id": 17085, "point_id": 67085}, {"courier_id": 295, "action": "pickup", "order_id": 16969, "point_id": 46969}, {"courier_id": 295, "action": "dropoff", "order_id": 16969, "point_id": 66969}, {"courier_id": 282, "action": "pickup", "order_id": 15970, "point_id": 45970}, {"courier_id": 282, "action": "dropoff", "order_id": 15970, "point_id": 65970}, {"courier_id": 240, "action": "pickup", "order_id": 16809, "point_id": 46809}, {"courier_id": 240, "action": "dropoff", "order_id": 16809, "point_id": 66809}, {"courier_id": 214, "action": "pickup", "order_id": 17041, "point_id": 47041}, {"courier_id": 214, "action": "dropoff", "order_id": 17041, "point_id": 67041}, {"courier_id": 293, "action": "pickup", "order_id": 16986, "point_id": 46986}, {"courier_id": 293, "action": "dropoff", "order_id": 16986, "point_id": 66986}, {"courier_id": 191, "action": "pickup", "order_id": 17207, "point_id": 47207}, {"courier_id": 191, "action": "dropoff", "order_id": 17207, "point_id": 67207}, {"courier_id": 243, "action": "pickup", "order_id": 17228, "point_id": 47228}, {"courier_id": 243, "action": "dropoff", "order_id": 17228, "point_id": 67228}, {"courier_id": 287, "action": "pickup", "order_id": 17192, "point_id": 47192}, {"courier_id": 287, "action": "dropoff", "order_id": 17192, "point_id": 67192}, {"courier_id": 249, "action": "pickup", "order_id": 10082, "point_id": 40082}, {"courier_id": 249, "action": "dropoff", "order_id": 10082, "point_id": 60082}, {"courier_id": 215, "action": "pickup", "order_id": 17181, "point_id": 47181}, {"courier_id": 215, "action": "dropoff", "order_id": 17181, "point_id": 67181}, {"courier_id": 269, "action": "pickup", "order_id": 15761, "point_id": 45761}, {"courier_id": 269, "action": "dropoff", "order_id": 15761, "point_id": 65761}, {"courier_id": 177, "action": "pickup", "order_id": 17194, "point_id": 47194}, {"courier_id": 177, "action": "dropoff", "order_id": 17194, "point_id": 67194}, {"courier_id": 253, "action": "pickup", "order_id": 17227, "point_id": 47227}, {"courier_id": 253, "action": "dropoff", "order_id": 17227, "point_id": 67227}]